cybersf/__init__.py
cybersf/__main__.py
cybersf/__version__.py
cybersf/console.py
cybersf/core/__init__.py
cybersf/core/config.py
cybersf/core/hosts.py
cybersf/core/menu.py
cybersf/core/repo.py
cybersf/core/usernames.py
cybersf/core/utilities.py
cybersf/information_gathering/__init__.py
cybersf/information_gathering/cli.py
cybersf/information_gathering/gitgraber.py
cybersf/information_gathering/hydrarecon.py
cybersf/information_gathering/s3scanner.py
cybersf/information_gathering/sherlock.py
cybersf/information_gathering/sqlmap.py
cybersf/information_gathering/striker.py
cybersf/information_gathering/sublist3r.py
cybersf/networking/__init__.py
cybersf/networking/bettercap.py
cybersf/networking/cli.py
cybersf/networking/nmap.py
cybersf/obfuscation/__init__.py
cybersf/obfuscation/cli.py
cybersf/obfuscation/cuteit.py
cybersf/passwords/__init__.py
cybersf/passwords/changeme.py
cybersf/passwords/cli.py
cybersf/passwords/cr3dov3r.py
cybersf/passwords/cupp.py
cybersf/passwords/hash_buster.py
cybersf/passwords/traitor.py
cybersf/redteam_tools/__init__.py
cybersf/redteam_tools/cli.py
cybersf/redteam_tools/nuclei.py
cybersf/web_apps/__init__.py
cybersf/web_apps/cli.py
cybersf/web_apps/photon.py
cybersf/web_apps/xsstrike.py
cybersf-3.2.9.dist-info/LICENSE
cybersf-3.2.9.dist-info/METADATA
cybersf-3.2.9.dist-info/WHEEL
cybersf-3.2.9.dist-info/entry_points.txt
cybersf-3.2.9.dist-info/top_level.txt
cybersf-3.2.9.dist-info/RECORD
