Metadata-Version: 2.1
Name: cybersf
Version: 3.2.9
Summary: A Modular Penetration Testing Framework
Home-page: https://khulnasoft.com/
Author: khulnasoft
Author-email: contact@khulnasoft.com
License: MIT
Project-URL: Packages, https://github.com/khulnasoft/cybersf/blob/main/PACKAGES.md
Project-URL: Changelog, https://github.com/khulnasoft/cybersf/blob/main/CHANGELOG.md
Project-URL: Funding, https://github.com/sponsors/thehappydinoa
Project-URL: Tracker, https://github.com/khulnasoft/cybersf/issues
Project-URL: Source, https://github.com/khulnasoft/cybersf
Keywords: cybersf
Platform: UNKNOWN
Classifier: Topic :: Internet
Classifier: Topic :: Security
Classifier: Framework :: Flake8
Classifier: Environment :: Console
Classifier: Natural Language :: English
Classifier: Operating System :: OS Independent
Classifier: License :: OSI Approved :: MIT License
Classifier: Programming Language :: Python
Classifier: Programming Language :: Python :: 3 :: Only
Classifier: Programming Language :: Python :: 3
Classifier: Programming Language :: Python :: 3.7
Classifier: Programming Language :: Python :: 3.8
Classifier: Programming Language :: Python :: 3.9
Classifier: Programming Language :: Python :: 3.10
Classifier: Programming Language :: Python :: 3.11
Classifier: Programming Language :: Python :: Implementation :: PyPy
Requires-Python: >=3.7.0
Requires-Dist: distro >=1.7.0
Requires-Dist: GitPython >=3.1.3
Requires-Dist: requests >=2.23.0
Requires-Dist: rich >=9.2.0
Provides-Extra: dev
Requires-Dist: black ==24.4.2 ; extra == 'dev'
Requires-Dist: flake8 ==7.0.0 ; extra == 'dev'
Requires-Dist: flake8-black ==0.3.6 ; extra == 'dev'
Requires-Dist: flake8-comprehensions ==3.14.0 ; extra == 'dev'
Requires-Dist: flake8-simplify ==0.21.0 ; extra == 'dev'
Requires-Dist: isort ==5.13.2 ; extra == 'dev'
Requires-Dist: mypy ==1.10.0 ; extra == 'dev'
Requires-Dist: pre-commit ==3.6.0 ; extra == 'dev'
Requires-Dist: twine ==4.0.2 ; extra == 'dev'
